LICENSE
README.md
pyproject.toml
setup.py
fluq/__init__.py
fluq/_util.py
fluq/column.py
fluq/frame.py
fluq/render.py
fluq/sql.py
fluq.egg-info/PKG-INFO
fluq.egg-info/SOURCES.txt
fluq.egg-info/dependency_links.txt
fluq.egg-info/top_level.txt
fluq/expression/__init__.py
fluq/expression/base.py
fluq/expression/clause.py
fluq/expression/datatype.py
fluq/expression/function.py
fluq/expression/join.py
fluq/expression/literals.py
fluq/expression/operator.py
fluq/expression/query.py
fluq/expression/selectable.py
fluq/expression/set_operation.py
fluq/parse/__init__.py
fluq/parse/parse.py
test/__init__.py
test/test__util.py
test/test_column.py
test/test_frame.py
test/test_parse.py
test/test_render.py
test/test_sql.py
test/test_expression/__init__.py
test/test_expression/test_base.py
test/test_expression/test_clause.py
test/test_expression/test_datatype.py
test/test_expression/test_function.py
test/test_expression/test_join.py
test/test_expression/test_operator.py
test/test_expression/test_query.py
test/test_expression/test_set_operation.py