Metadata-Version: 2.1
Name: fluq
Version: 0.1.5
Summary: FLUent Queries - A set of utilities and an intuitive API for constructing SQL queries programmatically
Home-page: https://github.com/AviadKlein/fluq
Author: Aviad Klein
Author-email: Aviad Klein <aviad.klein@gmail.com>
Project-URL: Homepage, https://github.com/AviadKlein/fluq
Classifier: Programming Language :: Python :: 3
Classifier: License :: OSI Approved :: MIT License
Classifier: Operating System :: OS Independent
Requires-Python: >=3.11
License-File: LICENSE
